elegantmotd/__init__.py
elegantmotd/__main__.py
elegantmotd/constants.py
elegantmotd/cpu.py
elegantmotd/disk.py
elegantmotd/load.py
elegantmotd/loggedinusers.py
elegantmotd/memory.py
elegantmotd/motd.py
elegantmotd/network.py
elegantmotd/process.py
elegantmotd/sysinfo.py
elegantmotd/temperature.py
elegantmotd/themes.py
elegantmotd-1.0.0.dist-info/METADATA
elegantmotd-1.0.0.dist-info/WHEEL
elegantmotd-1.0.0.dist-info/entry_points.txt
elegantmotd-1.0.0.dist-info/RECORD
