Metadata-Version: 2.3
Name: elegantmotd
Version: 1.0.0
Summary: A visually appealing and informative Message of the Day (MOTD) generator for Linux systems.
License: MIT
Keywords: motd,system,information,console,dashboard
Author: emerick-biron
Requires-Python: >=3.10,<4.0
Classifier: License :: OSI Approved :: MIT License
Classifier: Programming Language :: Python :: 3
Classifier: Programming Language :: Python :: 3.10
Classifier: Programming Language :: Python :: 3.11
Classifier: Programming Language :: Python :: 3.12
Classifier: Programming Language :: Python :: 3.13
Requires-Dist: art (>=6.4,<7.0)
Requires-Dist: distro (>=1.9.0,<2.0.0)
Requires-Dist: psutil (>=6.1.1,<7.0.0)
Requires-Dist: rich (>=13.9.4,<14.0.0)
Requires-Dist: rich-click (>=1.8.5,<2.0.0)
Project-URL: Homepage, https://github.com/emerick-biron/elegantmotd
Project-URL: Repository, https://github.com/emerick-biron/elegantmotd.git
